Metadata-Version: 2.1
Name: cosyvoice
Version: 0.0.8
Summary: CosyVoice TTS with multilangual support
Home-page: https://github.com/lucasjinreal/CosyVoice
Author: Lucas Jin
Author-email: jinfagang19@163.com
License: GPL-3.0
Keywords: deep learning,script helper,tools
Platform: any
Classifier: Operating System :: OS Independent
Classifier: Development Status :: 4 - Beta
Classifier: Intended Audience :: Developers
Classifier: Topic :: Education
Classifier: Topic :: Scientific/Engineering
Classifier: Topic :: Scientific/Engineering :: Artificial Intelligence
Classifier: Topic :: Scientific/Engineering :: Image Recognition
Classifier: License :: OSI Approved :: GNU General Public License v3 (GPLv3)
Classifier: Programming Language :: Python :: 3
Classifier: Programming Language :: Python :: 3.6
Classifier: Programming Language :: Python :: 3.7
Classifier: Programming Language :: Python :: 3.8
Classifier: Programming Language :: Python :: 3.9
License-File: LICENSE
